odoo/addons/sale_timesheet_invoice_description/README.rst
odoo/addons/sale_timesheet_invoice_description/__init__.py
odoo/addons/sale_timesheet_invoice_description/__manifest__.py
odoo/addons/sale_timesheet_invoice_description/i18n/ar.po
odoo/addons/sale_timesheet_invoice_description/i18n/bg.po
odoo/addons/sale_timesheet_invoice_description/i18n/bs.po
odoo/addons/sale_timesheet_invoice_description/i18n/ca.po
odoo/addons/sale_timesheet_invoice_description/i18n/cs.po
odoo/addons/sale_timesheet_invoice_description/i18n/da.po
odoo/addons/sale_timesheet_invoice_description/i18n/de.po
odoo/addons/sale_timesheet_invoice_description/i18n/el_GR.po
odoo/addons/sale_timesheet_invoice_description/i18n/en_GB.po
odoo/addons/sale_timesheet_invoice_description/i18n/es.po
odoo/addons/sale_timesheet_invoice_description/i18n/es_AR.po
odoo/addons/sale_timesheet_invoice_description/i18n/es_CL.po
odoo/addons/sale_timesheet_invoice_description/i18n/es_CO.po
odoo/addons/sale_timesheet_invoice_description/i18n/es_CR.po
odoo/addons/sale_timesheet_invoice_description/i18n/es_DO.po
odoo/addons/sale_timesheet_invoice_description/i18n/es_EC.po
odoo/addons/sale_timesheet_invoice_description/i18n/es_ES.po
odoo/addons/sale_timesheet_invoice_description/i18n/es_MX.po
odoo/addons/sale_timesheet_invoice_description/i18n/es_PE.po
odoo/addons/sale_timesheet_invoice_description/i18n/es_PY.po
odoo/addons/sale_timesheet_invoice_description/i18n/es_VE.po
odoo/addons/sale_timesheet_invoice_description/i18n/et.po
odoo/addons/sale_timesheet_invoice_description/i18n/eu.po
odoo/addons/sale_timesheet_invoice_description/i18n/fa.po
odoo/addons/sale_timesheet_invoice_description/i18n/fi.po
odoo/addons/sale_timesheet_invoice_description/i18n/fr.po
odoo/addons/sale_timesheet_invoice_description/i18n/gl.po
odoo/addons/sale_timesheet_invoice_description/i18n/he.po
odoo/addons/sale_timesheet_invoice_description/i18n/hr.po
odoo/addons/sale_timesheet_invoice_description/i18n/hr_HR.po
odoo11_addon_sale_timesheet_invoice_description-11.0.1.0.0.dist-info/DESCRIPTION.rst
odoo11_addon_sale_timesheet_invoice_description-11.0.1.0.0.dist-info/METADATA
odoo11_addon_sale_timesheet_invoice_description-11.0.1.0.0.dist-info/RECORD
odoo11_addon_sale_timesheet_invoice_description-11.0.1.0.0.dist-info/WHEEL
odoo11_addon_sale_timesheet_invoice_description-11.0.1.0.0.dist-info/metadata.json
odoo11_addon_sale_timesheet_invoice_description-11.0.1.0.0.dist-info/top_level.txt
